elytra/__init__.py
elytra/const.py
elytra/core.py
elytra/protocols.py
elytra/retry_transport.py
elytra/bedrock_realms/__init__.py
elytra/bedrock_realms/models.py
elytra/scripts/auth_device_code.py
elytra/scripts/authenticate.py
elytra/xbox/__init__.py
elytra/xbox/core.py
elytra/xbox/rta.py
elytra/xbox/club/__init__.py
elytra/xbox/club/models.py
elytra/xbox/message/__init__.py
elytra/xbox/message/models.py
elytra/xbox/peoplehub/__init__.py
elytra/xbox/peoplehub/models.py
elytra/xbox/profile/__init__.py
elytra/xbox/profile/models.py
elytra/xbox/social/__init__.py
elytra_ms-0.7.3.dist-info/METADATA
elytra_ms-0.7.3.dist-info/WHEEL
elytra_ms-0.7.3.dist-info/entry_points.txt
elytra_ms-0.7.3.dist-info/licenses/LICENSE
elytra_ms-0.7.3.dist-info/RECORD
