Metadata-Version: 2.3
Name: elytra-ms
Version: 0.7.3
Summary: A Python Library for various Microsoft APIs, including the Xbox and Bedrock Realms APIs.
Project-URL: Homepage, https://github.com/Astrea-Stellarium-Labs/elytra-ms
Author: AstreaTSS
License-Expression: MIT
License-File: LICENSE
Classifier: Development Status :: 3 - Alpha
Classifier: Framework :: AnyIO
Classifier: Framework :: AsyncIO
Classifier: Framework :: Trio
Classifier: Intended Audience :: Developers
Classifier: License :: OSI Approved :: MIT License
Classifier: Operating System :: OS Independent
Classifier: Programming Language :: Python :: 3
Classifier: Typing :: Typed
Requires-Python: >=3.10
Requires-Dist: anyio<5,>=4
Requires-Dist: exceptiongroup
Requires-Dist: httpx[http2]
Requires-Dist: msgspec
Requires-Dist: python-dateutil
Requires-Dist: typing-extensions
Requires-Dist: websockets
Provides-Extra: orjson
Requires-Dist: orjson; extra == 'orjson'
